<Properties StartupConfiguration="{086472C5-DD1F-4872-9BF1-9F9B633A376F}|Default">
  <MonoDevelop.Ide.Workbench ActiveDocument="Nutritracker/ingriedientListAnalyzer.cs">
    <Files>
      <File FileName="Nutritracker/frmDetailReport.cs" Line="116" Column="1" />
      <File FileName="Nutritracker/frmSearchFoods.cs" Line="227" Column="26" />
      <File FileName="Nutritracker/frmNewDBrel.cs" Line="339" Column="72" />
      <File FileName="Nutritracker/frmPairRelDB.cs" Line="17" Column="53" />
      <File FileName="Nutritracker/frmNewField.cs" Line="36" Column="100" />
      <File FileName="Nutritracker/frmActiveFields.cs" Line="168" Column="1" />
      <File FileName="Nutritracker/frmMain.cs" Line="233" Column="1" />
      <File FileName="Nutritracker/frmProfile.cs" Line="247" Column="50" />
      <File FileName="Nutritracker/ingriedientListAnalyzer.cs" Line="63" Column="30" />
    </Files>
  </MonoDevelop.Ide.Workbench>
  <MonoDevelop.Ide.Workspace ActiveConfiguration="Debug" />
  <MonoDevelop.Ide.DebuggingService.Breakpoints>
    <BreakpointStore>
      <Breakpoint file="/media/shane/RaptorWS/MonoProjects/Nutritracker/Nutritracker/frmPairRelDB.cs" relfile="Nutritracker/frmPairRelDB.cs" line="345" column="30" />
      <Breakpoint file="/media/shane/RaptorWS/MonoProjects/Nutritracker/Nutritracker/ingriedientListAnalyzer.cs" relfile="Nutritracker/ingriedientListAnalyzer.cs" line="66" column="78" />
    </BreakpointStore>
  </MonoDevelop.Ide.DebuggingService.Breakpoints>
  <MonoDevelop.Ide.DebuggingService.PinnedWatches />
  <MonoDevelop.Ide.ItemProperties.Nutritracker PreferredExecutionTarget="MonoDevelop.Default" />
  <AuthorInfo Name="Shane" Email="mathmuncher11@gmail.com" Copyright="GNU General Public License v3.0" Company="" Trademark="" />
  <MultiItemStartupConfigurations />
</Properties>