<Properties StartupConfiguration="{086472C5-DD1F-4872-9BF1-9F9B633A376F}|Default">
  <MonoDevelop.Ide.Workbench ActiveDocument="Nutritracker/frmActiveFields.cs">
    <Files>
      <File FileName="Nutritracker/frmCustomFood.cs" Line="487" Column="92" />
      <File FileName="Nutritracker/frmDetailReport.cs" Line="27" Column="10" />
      <File FileName="Nutritracker/frmActiveFields.cs" Line="87" Column="21" />
      <File FileName="Nutritracker/frmManageDB.cs" Line="637" Column="1" />
    </Files>
  </MonoDevelop.Ide.Workbench>
  <MonoDevelop.Ide.Workspace ActiveConfiguration="Debug" />
  <MonoDevelop.Ide.DebuggingService.Breakpoints>
    <BreakpointStore />
  </MonoDevelop.Ide.DebuggingService.Breakpoints>
  <MonoDevelop.Ide.DebuggingService.PinnedWatches />
  <MonoDevelop.Ide.ItemProperties.Nutritracker PreferredExecutionTarget="MonoDevelop.Default" />
  <AuthorInfo Name="Shane" Email="nutritracker02@gmail.com" Copyright="The GNU General Public License v3.0" Company="" Trademark="" />
  <MultiItemStartupConfigurations />
</Properties>